odoo10_addon_shopinvader_product_new-10.0.0.0.0.99.dev8-py3.8-nspkg.pth
odoo/addons/shopinvader_product_new/README.rst
odoo/addons/shopinvader_product_new/__init__.py
odoo/addons/shopinvader_product_new/__manifest__.py
odoo/addons/shopinvader_product_new/data/ir_cron.xml
odoo/addons/shopinvader_product_new/data/ir_export_product.xml
odoo/addons/shopinvader_product_new/i18n/shopinvader_product_new.pot
odoo/addons/shopinvader_product_new/models/__init__.py
odoo/addons/shopinvader_product_new/models/product_template.py
odoo/addons/shopinvader_product_new/tests/__init__.py
odoo/addons/shopinvader_product_new/tests/test_product.py
odoo/addons/shopinvader_product_new/views/product_template.xml
odoo10_addon_shopinvader_product_new-10.0.0.0.0.99.dev8.dist-info/METADATA
odoo10_addon_shopinvader_product_new-10.0.0.0.0.99.dev8.dist-info/WHEEL
odoo10_addon_shopinvader_product_new-10.0.0.0.0.99.dev8.dist-info/namespace_packages.txt
odoo10_addon_shopinvader_product_new-10.0.0.0.0.99.dev8.dist-info/top_level.txt
odoo10_addon_shopinvader_product_new-10.0.0.0.0.99.dev8.dist-info/RECORD
